src/__init__.py
src/cli.py
src/logger.py
src/controllers/__init__.py
src/controllers/scanner_controller.py
src/models/__init__.py
src/models/scanner_model.py
src/utils/__init__.py
src/utils/animations.py
src/views/__init__.py
src/views/scanner_view.py
serpant-1.2.0.dist-info/LICENSE
serpant-1.2.0.dist-info/METADATA
serpant-1.2.0.dist-info/WHEEL
serpant-1.2.0.dist-info/entry_points.txt
serpant-1.2.0.dist-info/top_level.txt
serpant-1.2.0.dist-info/RECORD
