Metadata-Version: 2.1
Name: serpant
Version: 1.2.0
Summary: A CLI tool for scanning directories for vulnerabilities
Home-page: https://github.com/Latrodect/wss-repo-vulnerability-finder
Author: Bahadir Nural
Author-email: bahadir.nural@outlook.com
Classifier: Programming Language :: Python :: 3
Classifier: License :: OSI Approved :: MIT License
Classifier: Operating System :: OS Independent
License-File: LICENSE
Requires-Dist: termcolor
Requires-Dist: colorlog
Requires-Dist: alive-progress
Requires-Dist: requests
